{
  "teas": [
    {
      "id": "1",
      "title": "White Snow",
      "category": "White tea",
      "author": "@nickname",
      "description": "Lorem ipsum",
      "ingredients": "mam tego naprawdę dosyć",
      "steepTime": "2-3",
      "steepTemp": "75-85",
      "region": "Chuijan",
      "vendor": "e-herbata.pl",
      "comments": "",
      "currentRating": 9.2
    },
    {
      "id": "1",
      "title": "White Snow",
      "category": "White tea",
      "author": "@nickname",
      "description": "Lorem ipsum",
      "ingredients": "mam tego naprawdę dosyć",
      "steepTime": "2-3",
      "steepTemp": "75-85",
      "region": "Chuijan",
      "vendor": "e-herbata.pl",
      "comments": "",
      "currentRating": 9.2
    },
    {
      "id": "1",
      "title": "White Snow",
      "category": "White tea",
      "author": "@nickname",
      "description": "Lorem ipsum",
      "ingredients": "mam tego naprawdę dosyć",
      "steepTime": "2-3",
      "steepTemp": "75-85",
      "region": "Chuijan",
      "vendor": "e-herbata.pl",
      "comments": "",
      "currentRating": 9.2
    },{
      "id": "1",
      "title": "White Snow",
      "category": "White tea",
      "author": "@nickname",
      "description": "Lorem ipsum",
      "ingredients": "mam tego naprawdę dosyć",
      "steepTime": "2-3",
      "steepTemp": "75-85",
      "region": "Chuijan",
      "vendor": "e-herbata.pl",
      "comments": "",
      "currentRating": 9.2
    },{
      "id": "1",
      "title": "White Snow",
      "category": "White tea",
      "author": "@nickname",
      "description": "Lorem ipsum",
      "ingredients": "mam tego naprawdę dosyć",
      "steepTime": "2-3",
      "steepTemp": "75-85",
      "region": "Chuijan",
      "vendor": "e-herbata.pl",
      "comments": "",
      "currentRating": 9.2
    },{
      "id": "1",
      "title": "White Snow",
      "category": "White tea",
      "author": "@nickname",
      "description": "Lorem ipsum",
      "ingredients": "mam tego naprawdę dosyć",
      "steepTime": "2-3",
      "steepTemp": "75-85",
      "region": "Chuijan",
      "vendor": "e-herbata.pl",
      "comments": "",
      "currentRating": 9.2
    },{
      "id": "1",
      "title": "White Snow",
      "category": "White tea",
      "author": "@nickname",
      "description": "Lorem ipsum",
      "ingredients": "mam tego naprawdę dosyć",
      "steepTime": "2-3",
      "steepTemp": "75-85",
      "region": "Chuijan",
      "vendor": "e-herbata.pl",
      "comments": "",
      "currentRating": 9.2
    }
]
}